{
  "timestamp": "2026-04-03T18:03:18.844823-03:00",
  "url": "https://vcbbank.sr/",
  "method": "GET",
  "headers": {
    "User-Agent": "Mozilla/5.0",
    "Accept-Encoding": "gzip, deflate",
    "Accept": "*/*",
    "Connection": "keep-alive"
  },
  "body": "None",
  "ip_local": "127.0.1.1",
  "traceroute": "traceroute to vcbbank.sr (23.235.204.26), 15 hops max\n  1   157.137.146.196  0.326ms  0.135ms  0.117ms \n  2   209.120.142.162  3.009ms  0.870ms  0.553ms \n  3   *  *  * \n  4   213.200.112.238  51.785ms  51.796ms  51.746ms \n  5   198.46.80.117  55.742ms  55.714ms  55.680ms \n  6   198.46.80.117  55.744ms  55.697ms  55.762ms \n  7   198.46.80.15  53.669ms  *  * \n  8   104.193.140.83  55.982ms  55.795ms  55.925ms \n  9   *  *  * \n 10   *  *  * \n 11   *  *  * \n 12   *  *  * \n 13   *  *  * \n 14   *  *  * \n 15   *  *  * \n"
}