{
  "timestamp": "2026-01-31T06:39:41.108542-03:00",
  "url": "https://www.godo.sr/nl/wisselkoersnoteringen/",
  "method": "GET",
  "headers": {
    "user-agent": "Mozilla/5.0 (Windows NT 10.0; Win64; x64) AppleWebKit/537.36 (KHTML, like Gecko) Chrome/124.0.0.0 Safari/537.36",
    "accept": "*/*",
    "accept-language": "nl-NL,nl;q=0.9,en;q=0.8",
    "connection": "keep-alive"
  },
  "body": "None",
  "ip_local": "127.0.1.1",
  "traceroute": "traceroute to www.godo.sr.cdn.cloudflare.net (172.66.154.95), 15 hops max\n  1   157.137.146.154  0.322ms  0.266ms  0.204ms \n  2   140.204.28.36  10.200ms  10.302ms  10.008ms \n  3   *  *  * \n  4   141.101.72.83  11.634ms  11.069ms  11.876ms \n  5   172.66.154.95  10.696ms  10.594ms  10.658ms \n"
}