{
  "timestamp": "2026-01-21T22:53:54.845938-03:00",
  "url": "https://www.godo.sr/nl/wisselkoersnoteringen/",
  "method": "GET",
  "headers": {
    "user-agent": "Mozilla/5.0 (Windows NT 10.0; Win64; x64) AppleWebKit/537.36 (KHTML, like Gecko) Chrome/124.0.0.0 Safari/537.36",
    "accept": "*/*",
    "accept-language": "nl-NL,nl;q=0.9,en;q=0.8",
    "connection": "keep-alive"
  },
  "body": "None",
  "ip_local": "127.0.1.1",
  "traceroute": "traceroute to www.godo.sr.cdn.cloudflare.net (172.66.154.95), 15 hops max\n  1   157.137.146.66  0.302ms  0.182ms  0.150ms \n  2   140.204.28.36  38.116ms  11.663ms  11.764ms \n  3   140.204.28.37  11.012ms  *  20.377ms \n  4   141.101.72.21  13.073ms  12.248ms  12.697ms \n  5   172.66.154.95  10.550ms  10.614ms  10.746ms \n"
}