{
  "timestamp": "2026-01-17T00:30:41.120716-03:00",
  "url": "https://www.cme.sr/Home/GetTodaysExchangeRates/?BusinessDate=2026-01-17",
  "method": "POST",
  "headers": {
    "User-Agent": "Mozilla/5.0 (Windows NT 10.0; Win64; x64) AppleWebKit/537.36 (KHTML, like Gecko) Chrome/139.0.0.0 Safari/537.36",
    "Accept": "*/*",
    "Accept-Language": "es-US,es-419;q=0.9,es;q=0.8,en;q=0.7,nl;q=0.6",
    "Accept-Encoding": "gzip, deflate",
    "Origin": "https://www.cme.sr",
    "Referer": "https://www.cme.sr/",
    "X-Requested-With": "XMLHttpRequest",
    "Cache-Control": "no-cache",
    "Pragma": "no-cache",
    "Content-Length": "0"
  },
  "body": "None",
  "ip_local": "127.0.1.1",
  "traceroute": "traceroute to www.cme.sr (172.67.142.118), 15 hops max\n  1   157.137.146.166  0.286ms  0.137ms  0.125ms \n  2   140.204.28.36  10.240ms  10.966ms  10.014ms \n  3   140.204.28.37  10.807ms  10.850ms  * \n  4   141.101.72.102  10.791ms  11.266ms  11.569ms \n  5   172.67.142.118  10.555ms  10.600ms  10.668ms \n"
}